bear_shelf/__init__.py
bear_shelf/__main__.py
bear_shelf/_logger.py
bear_shelf/_timer.py
bear_shelf/config.py
bear_shelf/models.py
bear_shelf/py.typed
bear_shelf/_internal/__init__.py
bear_shelf/_internal/_cmds.py
bear_shelf/_internal/_info.py
bear_shelf/_internal/_version.py
bear_shelf/_internal/_version.pyi
bear_shelf/_internal/_versioning.py
bear_shelf/_internal/cli.py
bear_shelf/_internal/debug.py
bear_shelf/database/__init__.py
bear_shelf/database/_extra.py
bear_shelf/database/base_manager.py
bear_shelf/database/base_manager.pyi
bear_shelf/database/config.py
bear_shelf/database/schemas.py
bear_shelf/datastore/README.md
bear_shelf/datastore/__init__.py
bear_shelf/datastore/base_settings.py
bear_shelf/datastore/columns.py
bear_shelf/datastore/columns.pyi
bear_shelf/datastore/common.py
bear_shelf/datastore/database.py
bear_shelf/datastore/header_data.py
bear_shelf/datastore/middleware.py
bear_shelf/datastore/record.py
bear_shelf/datastore/unified_data.py
bear_shelf/datastore/adapter/__init__.py
bear_shelf/datastore/adapter/jsonl/__init__.py
bear_shelf/datastore/adapter/jsonl/_convert.py
bear_shelf/datastore/adapter/jsonl/line_types.py
bear_shelf/datastore/adapter/xml/__init__.py
bear_shelf/datastore/adapter/xml/deserialize.py
bear_shelf/datastore/adapter/xml/schemas.py
bear_shelf/datastore/adapter/xml/serialize.py
bear_shelf/datastore/storage/__init__.py
bear_shelf/datastore/storage/_common.py
bear_shelf/datastore/storage/json.py
bear_shelf/datastore/storage/jsonl.py
bear_shelf/datastore/storage/memory.py
bear_shelf/datastore/storage/msgpack.py
bear_shelf/datastore/storage/nix.py
bear_shelf/datastore/storage/toml.py
bear_shelf/datastore/storage/toon.py
bear_shelf/datastore/storage/xml.py
bear_shelf/datastore/storage/yaml.py
bear_shelf/datastore/tables/__init__.py
bear_shelf/datastore/tables/data.py
bear_shelf/datastore/tables/handler.py
bear_shelf/datastore/tables/holder.py
bear_shelf/datastore/tables/protocol.py
bear_shelf/datastore/tables/table.py
bear_shelf-0.3.10.dist-info/METADATA
bear_shelf-0.3.10.dist-info/WHEEL
bear_shelf-0.3.10.dist-info/entry_points.txt
bear_shelf-0.3.10.dist-info/RECORD
