Metadata-Version: 2.4
Name: bear-shelf
Version: 0.3.10
Summary: A lightweight document storage system with SQLAlchemy dialect support. Where your data or honey, hibernates.
Author-email: chaz <bright.lid5647@fastmail.com>
Requires-Python: >=3.12
Requires-Dist: bear-config>=1.0.2
Requires-Dist: bear-epoch-time>=1.2.9
Requires-Dist: codec-cub>=0.0.15
Requires-Dist: frozen-cub>=0.1.8
Requires-Dist: funcy-bear>=0.0.26
Requires-Dist: lazy-bear>=0.0.10
Requires-Dist: pydantic>=2.12.4
Requires-Dist: sqlalchemy>=2.0.43
Requires-Dist: tomlkit>=0.13.3
